{
  "name": "B. Div на Mod",
  "testType": "SINGLE",
  "input": {
    "type": "STANDARD",
    "fileName": "input.txt"
  },
  "output": {
    "type": "STANDARD",
    "fileName": "output.txt"
  },
  "tests": [
    {
      "input": "6 3\n",
      "output": "11\n",
      "index": 0,
      "active": true
    },
    {
      "input": "1 2\n",
      "output": "3\n",
      "index": 1,
      "active": true
    },
    {
      "input": "4 6\n",
      "output": "10\n",
      "index": 2,
      "active": true
    }
  ],
  "location": "src/main/java/com/prituladima/codeforce/contests/contest1085",
  "vmArgs": "-Xmx256M",
  "mainClass": "Main",
  "taskClass": "com.prituladima.codeforce.contests.contest1085.BDivNaMod",
  "checkerClass": "net.egork.chelper.checkers.TokenChecker",
  "checkerParameters": "",
  "testClasses": [],
  "date": "2018.12.23",
  "contestName": "Codeforces Round #528 (Div. 2, основан на Отборочном раунде 4 Технокубка 2019)",
  "truncate": true,
  "inputClass": "com.prituladima.codeforce.InputReader",
  "outputClass": "java.io.PrintWriter",
  "includeLocale": false,
  "failOnOverflow": false,
  "interactive": false,
  "interactor": "net.egork.chelper.tester.Interactor"
}