{
  "name" : "1877. Bicycle Codes",
  "testType" : "SINGLE",
  "input" : {
    "type" : "STANDARD",
    "fileName" : "input.txt"
  },
  "output" : {
    "type" : "STANDARD",
    "fileName" : "output.txt"
  },
  "tests" : [ {
    "input" : "0001\n0000\n",
    "output" : "no\n",
    "index" : 0,
    "active" : true
  }, {
    "input" : "0002\n0001\n",
    "output" : "yes\n",
    "index" : 1,
    "active" : true
  } ],
  "location" : "src/main/java/com/prituladima/codeforce",
  "vmArgs" : "-Xmx64M",
  "mainClass" : "Main",
  "taskClass" : "com.prituladima.codeforce.BicycleCodes",
  "checkerClass" : "net.egork.chelper.checkers.TokenChecker",
  "checkerParameters" : "",
  "testClasses" : [ ],
  "date" : "2019.11.05",
  "contestName" : "Timus - Ural Regional School Programming Contest 2011",
  "truncate" : true,
  "inputClass" : "com.prituladima.yaal.io.InputReader",
  "outputClass" : "com.prituladima.yaal.io.OutputWriter",
  "includeLocale" : false,
  "failOnOverflow" : true,
  "interactive" : false,
  "interactor" : "net.egork.chelper.tester.Interactor"
}